CHANGES.rst
MANIFEST.in
README.rst
setup.py
cynic/__init__.py
cynic/server.py
cynic/utils.py
cynic.egg-info/PKG-INFO
cynic.egg-info/SOURCES.txt
cynic.egg-info/dependency_links.txt
cynic.egg-info/entry_points.txt
cynic.egg-info/not-zip-safe
cynic.egg-info/requires.txt
cynic.egg-info/top_level.txt
cynic/handlers/__init__.py
cynic/handlers/base.py
cynic/handlers/httphtml.py
cynic/handlers/httpjson.py
cynic/handlers/httpnone.py
cynic/handlers/httpslow.py
cynic/handlers/log.py
cynic/handlers/noresp.py
cynic/handlers/reset.py
cynic/handlers/rnd.py