Metadata-Version: 1.1
Name: cynic
Version: 1.0
Summary: Test harness to make your system under test cynical
Home-page: https://github.com/rspivak/cynic
Author: Ruslan Spivak
Author-email: ruslan.spivak@gmail.com
License: MIT
Platform: UNKNOWN
Classifier: Intended Audience :: Developers
Classifier: License :: OSI Approved :: MIT License
Classifier: Programming Language :: Python
Classifier: Topic :: Software Development :: Testing
Classifier: Operating System :: Unix
